kawin/Constants.py
kawin/GenericModel.py
kawin/PlotUtils.py
kawin/__init__.py
kawin/diffusion/Diffusion.py
kawin/diffusion/DiffusionParameters.py
kawin/diffusion/Homogenization.py
kawin/diffusion/HomogenizationParameters.py
kawin/diffusion/Plot.py
kawin/diffusion/SinglePhase.py
kawin/diffusion/__init__.py
kawin/diffusion/mesh/FVM1D.py
kawin/diffusion/mesh/FVM2D.py
kawin/diffusion/mesh/MeshBase.py
kawin/diffusion/mesh/__init__.py
kawin/precipitation/KWNBase.py
kawin/precipitation/KWNEuler.py
kawin/precipitation/NucleationRate.py
kawin/precipitation/Plot.py
kawin/precipitation/PopulationBalance.py
kawin/precipitation/PrecipitationParameters.py
kawin/precipitation/StoppingConditions.py
kawin/precipitation/TimeTemperaturePrecipitation.py
kawin/precipitation/__init__.py
kawin/precipitation/coupling/GrainGrowth.py
kawin/precipitation/coupling/Strength.py
kawin/precipitation/coupling/__init__.py
kawin/precipitation/parameters/EffectiveDiffusion.py
kawin/precipitation/parameters/ElasticFactors.py
kawin/precipitation/parameters/LebedevNodes.py
kawin/precipitation/parameters/Nucleation.py
kawin/precipitation/parameters/ShapeFactors.py
kawin/precipitation/parameters/Volume.py
kawin/precipitation/parameters/__init__.py
kawin/solver/Iterators.py
kawin/solver/Solver.py
kawin/solver/__init__.py
kawin/tests/__init__.py
kawin/tests/datasets.py
kawin/tests/test_PBM.py
kawin/tests/test_diffusion.py
kawin/tests/test_elasticFactors.py
kawin/tests/test_nucleation.py
kawin/tests/test_plotting.py
kawin/tests/test_precipitation.py
kawin/tests/test_shapeFactors.py
kawin/tests/test_solver.py
kawin/tests/test_strength.py
kawin/tests/test_surrogate.py
kawin/tests/test_thermodynamics.py
kawin/thermo/BinTherm.py
kawin/thermo/FreeEnergyHessian.py
kawin/thermo/LocalEquilibrium.py
kawin/thermo/Mobility.py
kawin/thermo/MultiTherm.py
kawin/thermo/Surrogate.py
kawin/thermo/Thermodynamics.py
kawin/thermo/__init__.py
kawin/thermo/utils.py
kawin-0.4.0.dist-info/licenses/LICENSE.txt
kawin-0.4.0.dist-info/METADATA
kawin-0.4.0.dist-info/WHEEL
kawin-0.4.0.dist-info/top_level.txt
kawin-0.4.0.dist-info/RECORD
