Metadata-Version: 2.4
Name: kawin
Version: 0.4.0
Summary: Tool for simulating precipitation using the KWN model coupled with Calphad.
Author-email: Nicholas Ury <nury12n@gmail.com>
License: MIT
Project-URL: Homepage, https://kawin.org
Classifier: Development Status :: 3 - Alpha
Classifier: Intended Audience :: Science/Research
Classifier: Topic :: Scientific/Engineering :: Physics
Classifier: Topic :: Scientific/Engineering :: Chemistry
Classifier: License :: OSI Approved :: MIT License
Classifier: Programming Language :: Python :: 3
Requires-Python: >=3.11
License-File: LICENSE.txt
Requires-Dist: matplotlib>=3.3
Requires-Dist: numpy>=2.0
Requires-Dist: pycalphad>=0.11
Requires-Dist: scipy
Requires-Dist: setuptools_scm[toml]>=6.0
Dynamic: license-file
